romania/__init__.py
romania/cnp.py
romania/core.py
romania-0.0.1.dist-info/LICENSE
romania-0.0.1.dist-info/METADATA
romania-0.0.1.dist-info/WHEEL
romania-0.0.1.dist-info/top_level.txt
romania-0.0.1.dist-info/RECORD
