Metadata-Version: 2.1
Name: romania
Version: 0.0.1
Summary: Python tools for Romania data processing
Project-URL: Homepage, https://github.com/code4romania/pyromania/
Project-URL: Issues, https://github.com/code4romania/pyromania/issues
Project-URL: Changelog, https://github.com/code4romania/pyromania/blob/main/CHANGELOG.md
Project-URL: Download, https://github.com/code4romania/pyromania/tags
Classifier: Development Status :: 1 - Planning
Classifier: Intended Audience :: Developers
Classifier: License :: OSI Approved :: Mozilla Public License 2.0 (MPL 2.0)
Classifier: Operating System :: OS Independent
Classifier: Programming Language :: Python :: 3
Classifier: Topic :: Software Development
Classifier: Topic :: Software Development :: Libraries
Classifier: Topic :: Software Development :: Libraries :: Python Modules
Requires-Python: >=3.11
License-File: LICENSE
